Metadata-Version: 1.0
Name: unicodecsv
Version: 0.9.3
Summary: Python2's stdlib csv module is nice, but it doesn't support unicode. This module is a drop-in replacement which *does*.
Home-page: https://github.com/jdunck/python-unicodecsv
Author: Jeremy Dunck
Author-email: jdunck@gmail.com
License: BSD License
Platform: UNKNOWN
Classifier: Development Status :: 5 - Production/Stable
Classifier: Intended Audience :: Developers
Classifier: License :: OSI Approved :: BSD License
Classifier: Natural Language :: English
Classifier: Programming Language :: Python :: 2.5
Classifier: Programming Language :: Python :: 2.6
Classifier: Programming Language :: Python :: 2.7
Classifier: Programming Language :: Python :: Implementation :: CPython
